{
  "report_id": "PMO-0623-0627",
  "report_type": "周报",
  "report_period": "0623-0627",
  "start_date": "2025-06-23",
  "end_date": "2025-06-27",
  "report_date": "2025-06-27",
  "reporting_unit": "某总行条线PMO",
  "service_audience": "管理层",
  "source_form": "邮件式周报/双周报整理",
  "raw_text": "本期PMO周报（0623-0627）汇报如下，请您审阅。三个项目呈请您关注：\n1、医院行业“六策合一”定向推动。试点分行累计营销145家医院，较上周+20家；分行审批中6笔，合计敞口额度5.3亿；批复后督中1笔0.5亿；批复3笔，较上周+1笔，批复敞口4亿。\n风险提示：6月27日集团投管会后督对已批复项目汝阳人民医院下发风险提示函，存在医保回款率低、自身医疗收入不足及租赁强制执行记录三项风险；其他区县级医院也收到集团后督询问。\n2、自贸账户体系存款上量。FT政策与资负沟通，达成如下三项共识，政策无进一步调整空间，跨境部申请项目终止，建议同意。\n（1）外汇现场检查前，上海自贸分行须自行通过吸收FT账户存款补齐缺口，10月起，如FT资金池出现临时缺口，资负部将临时支持FT同业拆借；\n（2）外汇现场检查后，资负部将在确保收益前提下，考虑单独设立FT账户本外币FTP曲线，帮助分行实现FT存贷规模和币种双平衡；\n（3）关于FT外币存款突破自律上限，因人总行与上海人行意见不一致，上海自贸需明确区域监管政策和同业做法，并承担主体合规责任。\n3、香港分行战略发展规划。在欧总指导下，分行修订汇报提纲，计划本周内向总行提交更新版本。\n\n一、项目总览\n截至6月27日，条线共38个待办事项，其中“1+3”项目10项、其他重点事项28项；本周增加7个项目，更新5个项目，暂停5个项目。\n\n\n二、增加项目（7项）\n1、根据调优项目梳理，增加四项“关键增长点”和一项“调优”项目，分别是“港分联动业务”、“自贸账户体系存款上量”、“外币低息存款上量（外币存款付息率下行）”、“机构业务政策改革”以及“投行派生存款增存”。\n2、根据6月分行检视会要求，增加北京分行两项待办“存款提升规划”和“企康专项汇报”。\n三、更新项目（5项）\n1、结合部门最新汇报，更新三项项目要求，“结现增长点”、“供应链拓链拓客”、“中长期贷款（并购、银团、非房项目贷款）提高绝对规模和市场份额”。\n2、根据企康业务周报指示，更新“企康业务模式升级”项目要求。\n四、暂停项目（5项）\n根据批示暂停五个项目，“完善企康创新方案”、“银行、租赁对公贷款产品对比分析”，上海分行“制定科技金融试点方案”、“探索对公团队专业化行业化方案”和“研究资产负债业务‘量价平衡’发展建议方案”。\n五、进展中项目（21项）\n详情如附。\n\n公司金融管理委员会秘书处\n二零二五年六月二十七日\n\n\n\n\n\n\n",
  "overview": {
    "as_of": "6月27日",
    "total_items": 38
  },
  "new_items_count": 7,
  "in_progress_count": 21,
  "request_lines": [],
  "alert_lines": []
}